django_structured_json_field-1.2.0.dist-info/licenses/LICENSE
structured/__init__.py
structured/apps.py
structured/fields.py
structured/settings.py
structured/urls.py
structured/views.py
structured/cache/__init__.py
structured/cache/cache.py
structured/cache/engine.py
structured/cache/rel_info.py
structured/contrib/restframework.py
structured/pydantic/__init__.py
structured/pydantic/models.py
structured/pydantic/fields/__init__.py
structured/pydantic/fields/foreignkey.py
structured/pydantic/fields/queryset.py
structured/pydantic/fields/serializer.py
structured/static/css/structured-field-form.min.css
structured/static/js/structured-field-form.js
structured/static/js/structured-field-form.js.map
structured/static/js/structured-field-form.min.js
structured/static/libs/fontawesome/css/all.min.css
structured/static/libs/fontawesome/webfonts/fa-brands-400.eot
structured/static/libs/fontawesome/webfonts/fa-brands-400.svg
structured/static/libs/fontawesome/webfonts/fa-brands-400.ttf
structured/static/libs/fontawesome/webfonts/fa-brands-400.woff
structured/static/libs/fontawesome/webfonts/fa-brands-400.woff2
structured/static/libs/fontawesome/webfonts/fa-regular-400.eot
structured/static/libs/fontawesome/webfonts/fa-regular-400.svg
structured/static/libs/fontawesome/webfonts/fa-regular-400.ttf
structured/static/libs/fontawesome/webfonts/fa-regular-400.woff
structured/static/libs/fontawesome/webfonts/fa-regular-400.woff2
structured/static/libs/fontawesome/webfonts/fa-solid-900.eot
structured/static/libs/fontawesome/webfonts/fa-solid-900.svg
structured/static/libs/fontawesome/webfonts/fa-solid-900.ttf
structured/static/libs/fontawesome/webfonts/fa-solid-900.woff
structured/static/libs/fontawesome/webfonts/fa-solid-900.woff2
structured/static/libs/jsoneditor/jsoneditor.js
structured/static/libs/jsoneditor/jsoneditor.js.map
structured/static/libs/select2/select2.min.js
structured/static/libs/select2/select2.style.css
structured/templates/json-forms/widget.html
structured/utils/__init__.py
structured/utils/cast.py
django_structured_json_field-1.2.0.dist-info/METADATA
django_structured_json_field-1.2.0.dist-info/WHEEL
django_structured_json_field-1.2.0.dist-info/top_level.txt
django_structured_json_field-1.2.0.dist-info/RECORD
