Metadata-Version: 2.4
Name: django-structured-json-field
Version: 1.2.0
Summary: Django json field empowered by pydantic
Author-email: Lotrèk <gabriele@lotrek.it>
License: MIT
Project-URL: Homepage, https://github.com/lotrekagency/django-structured-json-field
Keywords: django,pydantic,django pydantic,django json,json schema,django form
Classifier: Environment :: Web Environment
Classifier: Framework :: Django
Classifier: Framework :: Django :: 4.2
Classifier: Framework :: Django :: 5.0
Classifier: Framework :: Django :: 5.1
Classifier: Framework :: Django :: 5.2
Classifier: Intended Audience :: Developers
Classifier: Programming Language :: Python
Classifier: Programming Language :: Python :: 3
Classifier: Programming Language :: Python :: 3.10
Classifier: Programming Language :: Python :: 3.11
Classifier: Programming Language :: Python :: 3.12
Classifier: Programming Language :: Python :: 3.13
Classifier: Programming Language :: Python :: 3.14
Requires-Python: >=3.10
License-File: LICENSE
Requires-Dist: djangorestframework<4.0.0,>=3.14.0
Requires-Dist: Django>=4.2
Requires-Dist: pydantic>=2.12
Dynamic: license-file
